iceaxe/__init__.py
iceaxe/alias_values.py
iceaxe/base.py
iceaxe/comparison.py
iceaxe/field.py
iceaxe/functions.py
iceaxe/generics.py
iceaxe/io.py
iceaxe/logging.py
iceaxe/modifications.py
iceaxe/postgres.py
iceaxe/py.typed
iceaxe/queries.py
iceaxe/queries_str.py
iceaxe/session.py
iceaxe/session_optimized.c
iceaxe/session_optimized.cpython-312-x86_64-linux-gnu.so
iceaxe/session_optimized.pyx
iceaxe/sql_types.py
iceaxe/typing.py
iceaxe/__tests__/__init__.py
iceaxe/__tests__/conf_models.py
iceaxe/__tests__/conftest.py
iceaxe/__tests__/docker_helpers.py
iceaxe/__tests__/helpers.py
iceaxe/__tests__/test_alias.py
iceaxe/__tests__/test_base.py
iceaxe/__tests__/test_comparison.py
iceaxe/__tests__/test_field.py
iceaxe/__tests__/test_helpers.py
iceaxe/__tests__/test_modifications.py
iceaxe/__tests__/test_queries.py
iceaxe/__tests__/test_queries_str.py
iceaxe/__tests__/test_session.py
iceaxe/__tests__/test_text_search.py
iceaxe/__tests__/benchmarks/__init__.py
iceaxe/__tests__/benchmarks/test_bulk_insert.py
iceaxe/__tests__/benchmarks/test_select.py
iceaxe/__tests__/migrations/__init__.py
iceaxe/__tests__/migrations/conftest.py
iceaxe/__tests__/migrations/test_action_sorter.py
iceaxe/__tests__/migrations/test_generator.py
iceaxe/__tests__/migrations/test_generics.py
iceaxe/__tests__/mountaineer/__init__.py
iceaxe/__tests__/mountaineer/dependencies/__init__.py
iceaxe/__tests__/mountaineer/dependencies/test_core.py
iceaxe/__tests__/schemas/__init__.py
iceaxe/__tests__/schemas/test_actions.py
iceaxe/__tests__/schemas/test_cli.py
iceaxe/__tests__/schemas/test_db_memory_serializer.py
iceaxe/__tests__/schemas/test_db_serializer.py
iceaxe/__tests__/schemas/test_db_stubs.py
iceaxe/migrations/__init__.py
iceaxe/migrations/action_sorter.py
iceaxe/migrations/cli.py
iceaxe/migrations/client_io.py
iceaxe/migrations/generator.py
iceaxe/migrations/migration.py
iceaxe/migrations/migrator.py
iceaxe/mountaineer/__init__.py
iceaxe-0.8.2.dist-info/METADATA
iceaxe-0.8.2.dist-info/WHEEL
iceaxe-0.8.2.dist-info/top_level.txt
iceaxe-0.8.2.dist-info/RECORD
iceaxe-0.8.2.dist-info/licenses/LICENSE
