Metadata-Version: 2.4
Name: iceaxe
Version: 0.8.2
Summary: A modern, fast ORM for Python.
Author-email: Pierce Freeman <pierce@freeman.vc>
Requires-Python: >=3.11
License-File: LICENSE
Requires-Dist: asyncpg<1,>=0.30
Requires-Dist: click>=8
Requires-Dist: pydantic<3,>=2
Requires-Dist: rich>=13
Dynamic: license-file
